shared_allocator/__init__.py
shared_allocator/bump.py
shared_allocator/freelist.py
shared_allocator/slab.py
shared_allocator-0.1.0.dist-info/METADATA
shared_allocator-0.1.0.dist-info/WHEEL
shared_allocator-0.1.0.dist-info/top_level.txt
shared_allocator-0.1.0.dist-info/RECORD
