Metadata-Version: 2.4
Name: shared_allocator
Version: 0.1.0
Summary: High-performance shared memory allocation for Python
Author-email: Raymond Chastain <RaymondLC92@protonmail.com>
License: MIT
Keywords: shared-memory,allocator,allocation,multiprocessing,ipc
Classifier: Development Status :: 4 - Beta
Classifier: Intended Audience :: Developers
Classifier: License :: OSI Approved :: MIT License
Classifier: Programming Language :: Python :: 3.13
Requires-Python: >=3.13.7
